<?xml version="1.0" encoding="utf-8"?>
<GameRolePlayNpcInformations xmlns:xsi="http://www.w3.org/2001/XMLSchema-instance" xmlns:xsd="http://www.w3.org/2001/XMLSchema">
  <contextualId>-1</contextualId>
  <look>
    <bonesId>1</bonesId>
    <skins>
      <unsignedInt>101</unsignedInt>
      <unsignedInt>1254</unsignedInt>
    </skins>
    <indexedColors>
      <int>99014558</int>
      <int>44676320</int>
      <int>77599257</int>
      <int>31834049</int>
      <int>60822041</int>
    </indexedColors>
    <scales>
      <int>145</int>
    </scales>
    <subentities />
  </look>
  <disposition>
    <cellId>257</cellId>
    <direction>3</direction>
  </disposition>
  <npcId>524</npcId>
  <sex>true</sex>
  <specialArtworkId>0</specialArtworkId>
  <canGiveQuest>false</canGiveQuest>
</GameRolePlayNpcInformations>