<?xml version="1.0" encoding="utf-8"?>
<GameRolePlayNpcInformations xmlns:xsi="http://www.w3.org/2001/XMLSchema-instance" xmlns:xsd="http://www.w3.org/2001/XMLSchema">
  <contextualId>-1</contextualId>
  <look>
    <bonesId>1</bonesId>
    <skins>
      <unsignedInt>31</unsignedInt>
      <unsignedInt>441</unsignedInt>
      <unsignedInt>128</unsignedInt>
    </skins>
    <indexedColors>
      <int>95259961</int>
      <int>37037160</int>
      <int>83033855</int>
      <int>32161890</int>
      <int>50505142</int>
    </indexedColors>
    <scales>
      <int>95</int>
    </scales>
    <subentities>
      <SubEntity>
        <bindingPointCategory>1</bindingPointCategory>
        <bindingPointIndex>0</bindingPointIndex>
        <subEntityLook>
          <bonesId>451</bonesId>
          <skins />
          <indexedColors />
          <scales>
            <int>65</int>
          </scales>
          <subentities />
        </subEntityLook>
      </SubEntity>
    </subentities>
  </look>
  <disposition>
    <cellId>361</cellId>
    <direction>3</direction>
  </disposition>
  <npcId>850</npcId>
  <sex>true</sex>
  <specialArtworkId>0</specialArtworkId>
  <canGiveQuest>false</canGiveQuest>
</GameRolePlayNpcInformations>